Metadata-Version: 1.1
Name: asrequests
Version: 0.1.1
Summary: Requests + asyncio
Home-page: https://github.com/HuberTRoy/asrequests
Author: cyrbuzz
Author-email: cyrbuzz@foxmail.com
License: MIT
Platform: any
Classifier: Environment :: Web Environment
Classifier: Intended Audience :: Developers
Classifier: License :: OSI Approved :: MIT License
Classifier: Operating System :: OS Independent
Classifier: Programming Language :: Python
Classifier: Topic :: Internet :: WWW/HTTP :: Dynamic Content
Classifier: Topic :: Software Development :: Libraries :: Python Modules
